<Properties StartupConfiguration="{CBCFFFFA-882E-429D-994A-30E86512B948}|Default">
  <MonoDevelop.Ide.Workbench ActiveDocument="TravelCommunity/Views/LoginPage.xaml.cs">
    <Files>
      <File FileName="TravelCommunity/Views/LoginPage.xaml" Line="59" Column="29" />
      <File FileName="TravelCommunity/Views/LoginPage.xaml.cs" Line="21" Column="23" />
    </Files>
  </MonoDevelop.Ide.Workbench>
  <MonoDevelop.Ide.Workspace ActiveConfiguration="Debug" />
  <MonoDevelop.Ide.DebuggingService.Breakpoints>
    <BreakpointStore />
  </MonoDevelop.Ide.DebuggingService.Breakpoints>
  <MonoDevelop.Ide.DebuggingService.PinnedWatches />
  <MultiItemStartupConfigurations />
  <DisabledProjects>
    <String>Droid/TravelCommunity.Droid.csproj</String>
  </DisabledProjects>
  <MonoDevelop.Ide.ItemProperties.TravelCommunity.iOS PreferredExecutionTarget="MonoDevelop.IPhone.IPhoneSimulatorTarget.FACE5AF0-81A1-486C-BE67-D611552341DB">
    <MonoDevelop.MacDev.AppleDevelopmentTeam />
  </MonoDevelop.Ide.ItemProperties.TravelCommunity.iOS>
</Properties>